{
    "safari.game.images.game.background.img":"background.jpg",
    "safari.game.images.game.background.w":"584",
    "safari.game.images.game.background.h":"408",

    "puz.test.1":{
                  "1":"000000010000000",
                  "2":"000000000000000",
                  "3":"000000000000000",
                  "4":"000000000000000",
                  "5":"000000000000000",
                  "6":"000000000000000",
                  "7":"000000000000000",
                  "8":"000000100000000"
                 },

    "puz.easy.1":{
                  "1":"103211000112301",
                  "2":"011121101121110",
                  "3":"011211121112110",
                  "4":"001321111123100",
                  "5":"000111121111000",
                  "6":"000011111110000",
                  "7":"000001121100000",
                  "8":"100000111000001"
                 },
    "puz.easy.1.metagame_tiles":"4",
    "puz.easy.1.name":"Lovely"
}